online_store/__init__.py
online_store/__main__.py
online_store/main.py
online_store/order_management.py
online_store/temp.py
online_store/user_management.py
yet_another_project_online_store-0.1.0.dist-info/METADATA
yet_another_project_online_store-0.1.0.dist-info/WHEEL
yet_another_project_online_store-0.1.0.dist-info/entry_points.txt
yet_another_project_online_store-0.1.0.dist-info/top_level.txt
yet_another_project_online_store-0.1.0.dist-info/RECORD
